bitweb_yespower.cp39-win32.pyd
bitweb_yespower-1.0.5.dist-info/METADATA
bitweb_yespower-1.0.5.dist-info/WHEEL
bitweb_yespower-1.0.5.dist-info/top_level.txt
bitweb_yespower-1.0.5.dist-info/RECORD
