Metadata-Version: 2.1
Name: bitweb-yespower
Version: 1.0.5
Summary: Bindings for yespower-1.0 proof of work used by bitweb
Home-page: https://github.com/bitweb-project/bitweb_yespower_python3
Author: mraksoll
Author-email: mraksoll4@gmail.com
License: UNKNOWN
Platform: UNKNOWN
